pyright_stubgen/__init__.py
pyright_stubgen/stubgen.py
pyright_stubgen-0.1.0.dist-info/METADATA
pyright_stubgen-0.1.0.dist-info/WHEEL
pyright_stubgen-0.1.0.dist-info/entry_points.txt
pyright_stubgen-0.1.0.dist-info/licenses/LICENSE
pyright_stubgen-0.1.0.dist-info/RECORD
