Metadata-Version: 2.3
Name: pyright-stubgen
Version: 0.1.0
Summary: stubgen using pyright
License: MIT License
License-File: LICENSE
Classifier: Development Status :: 4 - Beta
Classifier: Framework :: AsyncIO
Classifier: Programming Language :: Python :: 3
Classifier: Programming Language :: Python :: 3.9
Classifier: Programming Language :: Python :: 3.10
Classifier: Programming Language :: Python :: 3.11
Classifier: Programming Language :: Python :: 3.12
Classifier: Programming Language :: Python :: Implementation :: CPython
Requires-Python: >=3.9
Requires-Dist: anyio>=4
Requires-Dist: pyright
Requires-Dist: typing-extensions
